setup.py
lcse/__init__.py
lcse/aprofile.py
lcse/hvr_key.py
lcse/lut.py
lcse/restarta.py
lcse/rprofile.py
lcse/rtplot.py
lcse.egg-info/PKG-INFO
lcse.egg-info/SOURCES.txt
lcse.egg-info/dependency_links.txt
lcse.egg-info/requires.txt
lcse.egg-info/top_level.txt