Metadata-Version: 1.0
Name: lcse
Version: 8.0
Summary: Python modules for reading formats produced by LCSE codes
Home-page: http://lcse.umn.edu/
Author: Stou Sandalski
Author-email: sandalski@astro.umn.edu
License: Apache
Keywords: ppmstar cfd lut keys rprofile restart bob anp
Platform: UNKNOWN
